nvidia_pipecat/__init__.py
nvidia_pipecat/py.typed
nvidia_pipecat/frames/__init__.py
nvidia_pipecat/frames/action.py
nvidia_pipecat/frames/custom_view.py
nvidia_pipecat/frames/nvidia_rag.py
nvidia_pipecat/frames/riva.py
nvidia_pipecat/frames/system_prompt.py
nvidia_pipecat/frames/transcripts.py
nvidia_pipecat/pipeline/__init__.py
nvidia_pipecat/pipeline/ace_pipeline_runner.py
nvidia_pipecat/processors/__init__.py
nvidia_pipecat/processors/acknowledgment.py
nvidia_pipecat/processors/audio_util.py
nvidia_pipecat/processors/guardrail.py
nvidia_pipecat/processors/nvidia_context_aggregator.py
nvidia_pipecat/processors/nvidia_rtvi.py
nvidia_pipecat/processors/proactivity.py
nvidia_pipecat/processors/transcript_synchronization.py
nvidia_pipecat/processors/user_presence.py
nvidia_pipecat/processors/utils.py
nvidia_pipecat/serializers/ace_websocket.py
nvidia_pipecat/services/__init__.py
nvidia_pipecat/services/blingfire_text_aggregator.py
nvidia_pipecat/services/elevenlabs.py
nvidia_pipecat/services/nat_agent.py
nvidia_pipecat/services/nvidia_llm.py
nvidia_pipecat/services/nvidia_rag.py
nvidia_pipecat/services/riva_nmt.py
nvidia_pipecat/services/riva_speech.py
nvidia_pipecat/services/speech_planner.py
nvidia_pipecat/transports/__init__.py
nvidia_pipecat/transports/network/__init__.py
nvidia_pipecat/transports/network/ace_fastapi_websocket.py
nvidia_pipecat/transports/services/__init__.py
nvidia_pipecat/transports/services/ace_controller/__init__.py
nvidia_pipecat/transports/services/ace_controller/routers/register_apis_router.py
nvidia_pipecat/transports/services/ace_controller/routers/websocket_router.py
nvidia_pipecat/utils/__init__.py
nvidia_pipecat/utils/http_client.py
nvidia_pipecat/utils/logging.py
nvidia_pipecat/utils/message_broker.py
nvidia_pipecat-0.3.0.dist-info/METADATA
nvidia_pipecat-0.3.0.dist-info/WHEEL
nvidia_pipecat-0.3.0.dist-info/licenses/LICENSE
nvidia_pipecat-0.3.0.dist-info/RECORD
