Metadata-Version: 2.4
Name: nvidia-pipecat
Version: 0.3.0
Summary: NVIDIA Pipecat SDK
Project-URL: GitHub, https://github.com/NVIDIA/voice-agent-examples
Project-URL: Documentation, https://github.com/NVIDIA/voice-agent-examples/blob/main/README.md
Author-email: NVIDIA ACE <ace-dev@exchange.nvidia.com>
License: BSD 2-Clause License
License-File: LICENSE
Requires-Python: >=3.12
Requires-Dist: av>=13.0.0
Requires-Dist: blingfire>=0.1.8; platform_machine == 'x86_64' or platform_machine == 'AMD64'
Requires-Dist: fastapi>=0.115.7
Requires-Dist: hatchling>=1.27.0
Requires-Dist: langchain-nvidia-ai-endpoints>=0.3.8
Requires-Dist: nvidia-riva-client==2.20.0
Requires-Dist: onnxruntime>=1.20.1
Requires-Dist: openai>=1.58.1
Requires-Dist: pipecat-ai==0.0.85
Requires-Dist: python-dotenv>=1.0.1
Requires-Dist: rapidfuzz>=3.14.0
Requires-Dist: redis>=5.2.1
Requires-Dist: requests>=2.32.3
Requires-Dist: sentence-transformers>=3.3.1
Requires-Dist: torch>=2.5.1
Requires-Dist: transitions>=0.9.2
Requires-Dist: uvicorn>=0.34.0
Requires-Dist: websockets==13.1
Requires-Dist: wheel>=0.45.1
